stackloop/__init__.py
stackloop/__main__.py
stackloop/agent/__init__.py
stackloop/agent/setup.py
stackloop/cli/__init__.py
stackloop/cli/commands.py
stackloop/cli/display.py
stackloop/cli/prompts.py
stackloop/core/__init__.py
stackloop/core/agent_config.py
stackloop/core/code_fixer.py
stackloop/core/debug_session.py
stackloop/core/execution.py
stackloop/models/__init__.py
stackloop/models/corrected_code.py
stackloop/models/error_analysis.py
stackloop/models/execution_result.py
stackloop/models/session_config.py
stackloop/utils/__init__.py
stackloop/utils/constants.py
stackloop-1.0.3.dist-info/LICENSE
stackloop-1.0.3.dist-info/METADATA
stackloop-1.0.3.dist-info/WHEEL
stackloop-1.0.3.dist-info/entry_points.txt
stackloop-1.0.3.dist-info/RECORD
