Metadata-Version: 2.3
Name: stackloop
Version: 1.0.3
Summary: AI-powered debugging agent that automatically runs, analyzes, and fixes your code
Keywords: ai,debugging,automation,code-fixing,developer-tools
Author: Blessed Josiah
Author-email: blessed_josiah@yahoo.com
Requires-Python: >=3.10,<4.0
Classifier: Development Status :: 4 - Beta
Classifier: Intended Audience :: Developers
Classifier: Programming Language :: Python :: 3
Classifier: Programming Language :: Python :: 3.10
Classifier: Programming Language :: Python :: 3.11
Classifier: Programming Language :: Python :: 3.12
Classifier: Programming Language :: Python :: 3.13
Classifier: Topic :: Software Development :: Debuggers
Requires-Dist: pydantic-ai (>=1.12.0,<2.0.0)
Requires-Dist: pyfiglet (>=1.0.4,<2.0.0)
Requires-Dist: python-dotenv (>=1.2.1,<2.0.0)
Requires-Dist: questionary (>=2.1.1,<3.0.0)
Requires-Dist: rich (>=14.2.0,<15.0.0)
Requires-Dist: typer (>=0.20.0,<0.21.0)
Project-URL: Homepage, https://github.com/bjoxiah/stackloop
Project-URL: Repository, https://github.com/bjoxiah/stackloop
